MANIFEST.in
README.txt
distribute_setup.py
setup.py
dicompyler/__init__.py
dicompyler/credits.txt
dicompyler/dicomgui.py
dicompyler/dicomparser.py
dicompyler/dvhcalc.py
dicompyler/dvhdata.py
dicompyler/dvhdoses.py
dicompyler/guidvh.py
dicompyler/guiutil.py
dicompyler/license.txt
dicompyler/main.py
dicompyler/plugin.py
dicompyler/preferences.py
dicompyler/util.py
dicompyler/wxmpl.py
dicompyler.egg-info/PKG-INFO
dicompyler.egg-info/SOURCES.txt
dicompyler.egg-info/dependency_links.txt
dicompyler.egg-info/entry_points.txt
dicompyler.egg-info/not-zip-safe
dicompyler.egg-info/requires.txt
dicompyler.egg-info/top_level.txt
dicompyler/baseplugins/2dview.py
dicompyler/baseplugins/2dview.xrc
dicompyler/baseplugins/__init__.py
dicompyler/baseplugins/anonymize.py
dicompyler/baseplugins/anonymize.xrc
dicompyler/baseplugins/dvh.py
dicompyler/baseplugins/dvh.xrc
dicompyler/baseplugins/treeview.py
dicompyler/baseplugins/treeview.xrc
dicompyler/resources/accept.png
dicompyler/resources/book.png
dicompyler/resources/chart_bar.png
dicompyler/resources/chart_bar_error.png
dicompyler/resources/chart_curve.png
dicompyler/resources/chart_curve_error.png
dicompyler/resources/contrast_high.png
dicompyler/resources/dicomgui.xrc
dicompyler/resources/dicompyler.ico
dicompyler/resources/dicompyler_icon11_16.png
dicompyler/resources/dicompyler_logo.png
dicompyler/resources/error.png
dicompyler/resources/folder_user.png
dicompyler/resources/group.png
dicompyler/resources/guiutil.xrc
dicompyler/resources/magnifier_zoom_in.png
dicompyler/resources/magnifier_zoom_out.png
dicompyler/resources/main.xrc
dicompyler/resources/pencil.png
dicompyler/resources/pencil_error.png
dicompyler/resources/plugin.xrc
dicompyler/resources/preferences.xrc
dicompyler/resources/table_multiple.png
dicompyler/resources/user.png