Metadata-Version: 1.0
Name: dicompyler
Version: 0.4.1
Summary: Extensible radiation therapy research platform and viewer for DICOM and DICOM RT.
Home-page: http://code.google.com/p/dicompyler/
Author: Aditya Panchal
Author-email: apanchal@bastula.org
License: BSD License
Keywords: radiation therapy research python dicom dicom-rt
Platform: UNKNOWN
Classifier: License :: OSI Approved :: BSD License
Classifier: Intended Audience :: Developers
Classifier: Intended Audience :: Healthcare Industry
Classifier: Intended Audience :: Science/Research
Classifier: Development Status :: 4 - Beta
Classifier: Programming Language :: Python
Classifier: Programming Language :: Python :: 2.5
Classifier: Programming Language :: Python :: 2.6
Classifier: Programming Language :: Python :: 2.7
Classifier: Operating System :: OS Independent
Classifier: Topic :: Scientific/Engineering :: Medical Science Apps.
Classifier: Topic :: Scientific/Engineering :: Physics
Classifier: Topic :: Scientific/Engineering :: Visualization
